quotebot/__init__.py
quotebot/command_line.py
quotebot/jamesbrown.py
quotebot/quotes.csv
quotebot/randomquotes.py
randomquotebot-0.4.dist-info/METADATA
randomquotebot-0.4.dist-info/WHEEL
randomquotebot-0.4.dist-info/entry_points.txt
randomquotebot-0.4.dist-info/top_level.txt
randomquotebot-0.4.dist-info/RECORD
