Metadata-Version: 2.1
Name: randomquotebot
Version: 0.4
Summary: UNKNOWN
Home-page: UNKNOWN
License: UNKNOWN
Platform: UNKNOWN
Requires-Dist: colr
